xuserauth/__init__.py
xuserauth/auth_manager.py
xuserauth/exceptions.py
xuserauth/hashing.py
xuserauth/jwt_utils.py
xuserauth/models.py
xuserauth/roles.py
xuserauth/schemas.py
xuserauth/social/__init__.py
xuserauth/social/facebook.py
xuserauth/social/google.py
xuserauth-1.0.2.dist-info/licenses/LICENSE
xuserauth-1.0.2.dist-info/METADATA
xuserauth-1.0.2.dist-info/WHEEL
xuserauth-1.0.2.dist-info/top_level.txt
xuserauth-1.0.2.dist-info/RECORD
