Metadata-Version: 2.4
Name: xuserauth
Version: 1.0.2
Summary: 🔐 Pluggable Auth System for FastAPI — JWT, Roles, Google OAuth, Hashing, and Decorators
Author-email: Abdulbasit Ayinde Aliyu <you@example.com>
License: MIT
Keywords: fastapi,authentication,jwt,oauth,google,authorization,roles,decorators
Classifier: Development Status :: 5 - Production/Stable
Classifier: Programming Language :: Python :: 3
Classifier: Framework :: FastAPI
Classifier: License :: OSI Approved :: MIT License
Classifier: Operating System :: OS Independent
Requires-Python: >=3.8
License-File: LICENSE
Requires-Dist: fastapi
Requires-Dist: starlette
Requires-Dist: bcrypt
Requires-Dist: passlib
Requires-Dist: PyJWT
Requires-Dist: Authlib
Requires-Dist: httpx
Requires-Dist: python-jose
Requires-Dist: cryptography
Requires-Dist: ecdsa
Requires-Dist: pyasn
Requires-Dist: typing-extensions
Requires-Dist: pydantic
Requires-Dist: pydantic_core
Requires-Dist: annotated-types
Requires-Dist: typing-inspection
Requires-Dist: anyio
Requires-Dist: idna
Requires-Dist: certifi
Requires-Dist: h11
Requires-Dist: httpcore
Requires-Dist: colorama
Requires-Dist: six
Requires-Dist: cffi
Requires-Dist: pycparser
Requires-Dist: rsa
Provides-Extra: dev
Requires-Dist: pytest; extra == "dev"
Requires-Dist: pytest-asyncio; extra == "dev"
Requires-Dist: iniconfig; extra == "dev"
Requires-Dist: Pygments; extra == "dev"
Dynamic: license-file
